robinzhon-0.2.1.dist-info/METADATA
robinzhon-0.2.1.dist-info/WHEEL
robinzhon-0.2.1.dist-info/licenses/LICENSE
robinzhon/__init__.py
robinzhon/robinzhon.cpython-314-x86_64-linux-gnu.so
robinzhon-0.2.1.dist-info/RECORD
