Metadata-Version: 2.4
Name: robinzhon
Version: 0.2.1
Classifier: Development Status :: 4 - Beta
Classifier: Intended Audience :: Developers
Classifier: License :: OSI Approved :: MIT License
Classifier: Operating System :: OS Independent
Classifier: Programming Language :: Python
Classifier: Programming Language :: Python :: 3
Classifier: Programming Language :: Python :: 3.9
Classifier: Programming Language :: Python :: 3.10
Classifier: Programming Language :: Python :: 3.11
Classifier: Programming Language :: Python :: 3.12
Classifier: Programming Language :: Python :: 3.13
Classifier: Programming Language :: Rust
Classifier: Programming Language :: Python :: Implementation :: CPython
Classifier: Topic :: Software Development :: Libraries :: Python Modules
Classifier: Topic :: Internet :: WWW/HTTP
Classifier: Topic :: Utilities
Classifier: Typing :: Typed
License-File: LICENSE
Summary: Minimal, high-performance Python helpers for concurrent S3 object transfers
Keywords: s3,aws,download,s3-download,upload,s3-upload,performance,concurrent,async,rust,pyo3,rust-extension,cloud,storage,boto3
Home-Page: https://github.com/rohaquinlop/robinzhon
Author-email: Robin Quintero <rohaquinlop301@gmail.com>
License: MIT
Requires-Python: >=3.9
